{
  "name": "Home",
  "path": "/",
  "sections": [
    {
      "__resolveType": "site/sections/starstuff/StarBG.tsx",
      "numberOfStars": 10
    },
    {
      "__resolveType": "site/sections/ChatApp.tsx"
    },
    {
      "__resolveType": "site/sections/Waves.tsx"
    },
    {
      "__resolveType": "site/sections/About.tsx"
    },
    {
      "__resolveType": "website/sections/Seo/SeoV2.tsx",
      "noIndexing": true
    }
  ],
  "__resolveType": "website/pages/Page.tsx",
  "seo": {
    "__resolveType": "website/sections/Seo/SeoV2.tsx",
    "type": "website",
    "title": "Sailor",
    "description": "Exchange messages with other sailors",
    "themeColor": "#4c6e68",
    "disableIndexing": "true",
    "image": "https://ozksgdmyrqcxcwhnbepg.supabase.co/storage/v1/object/public/assets/11642/edc6f832-558d-4f3c-acdc-540e50638933",
    "favicon": "https://ozksgdmyrqcxcwhnbepg.supabase.co/storage/v1/object/public/assets/11642/2ce8f696-3909-4ae4-909c-f3486505bf07"
  }
}